odoo10_addon_hr_worked_days_from_timesheet-10.0.1.0.0.99.dev12-py2.7-nspkg.pth
odoo/addons/hr_worked_days_from_timesheet/README.rst
odoo/addons/hr_worked_days_from_timesheet/__init__.py
odoo/addons/hr_worked_days_from_timesheet/__manifest__.py
odoo/addons/hr_worked_days_from_timesheet/i18n/cs_CZ.po
odoo/addons/hr_worked_days_from_timesheet/i18n/de.po
odoo/addons/hr_worked_days_from_timesheet/i18n/es.po
odoo/addons/hr_worked_days_from_timesheet/i18n/fr.po
odoo/addons/hr_worked_days_from_timesheet/i18n/hr_worked_days_from_timesheet.pot
odoo/addons/hr_worked_days_from_timesheet/i18n/sl.po
odoo/addons/hr_worked_days_from_timesheet/models/__init__.py
odoo/addons/hr_worked_days_from_timesheet/models/hr_payslip.py
odoo/addons/hr_worked_days_from_timesheet/models/hr_payslip_worked_days.py
odoo/addons/hr_worked_days_from_timesheet/static/description/icon.png
odoo/addons/hr_worked_days_from_timesheet/tests/__init__.py
odoo/addons/hr_worked_days_from_timesheet/tests/test_worked_days_from_timesheet.py
odoo/addons/hr_worked_days_from_timesheet/views/hr_payslip_view.xml
odoo10_addon_hr_worked_days_from_timesheet-10.0.1.0.0.99.dev12.dist-info/METADATA
odoo10_addon_hr_worked_days_from_timesheet-10.0.1.0.0.99.dev12.dist-info/RECORD
odoo10_addon_hr_worked_days_from_timesheet-10.0.1.0.0.99.dev12.dist-info/WHEEL
odoo10_addon_hr_worked_days_from_timesheet-10.0.1.0.0.99.dev12.dist-info/namespace_packages.txt
odoo10_addon_hr_worked_days_from_timesheet-10.0.1.0.0.99.dev12.dist-info/top_level.txt
