Metadata-Version: 2.1
Name: odoo10-addon-hr-worked-days-from-timesheet
Version: 10.0.1.0.0.99.dev12
Summary: Adds a button to import worked days from timesheet.
Home-page: https://www.savoirfairelinux.com/
Author: Savoir-faire Linux, Acysos S.L., Eficent, Serpent Consulting Services Pvt. Ltd.,Odoo Community Association (OCA)
Author-email: support@odoo-community.org
License: AGPL-3
Platform: UNKNOWN
Classifier: Programming Language :: Python
Classifier: Framework :: Odoo
Classifier: License :: OSI Approved :: GNU Affero General Public License v3
Requires-Python: ~=2.7
Requires-Dist: odoo (<10.1dev,>=10.0)
